diacamma/__init__.py
diacamma/asso/Diacamma.ico
diacamma/asso/Diacamma.png
diacamma/asso/DiacammaAsso.ico
diacamma/asso/DiacammaAsso.jpg
diacamma/asso/DiacammaAsso.png
diacamma/asso/__init__.py
diacamma/asso/appli_settings.py
diacamma/asso/build
diacamma/asso/diacamma_asso.css
diacamma/asso/fond.jpg
diacamma/asso/init_belgium.csv
diacamma/asso/init_french-complet.csv
diacamma/asso/init_french-simple.csv
diacamma/asso/tests.py
diacamma/asso/views.py
diacamma/asso/docs/build_en/doctrees/environment.pickle
diacamma/asso/docs/build_en/doctrees/first_step.doctree
diacamma/asso/docs/build_en/doctrees/index.doctree
diacamma/asso/docs/build_en/doctrees/presentation.doctree
diacamma/asso/docs/build_fr/doctrees/environment.pickle
diacamma/asso/docs/build_fr/doctrees/first_step.doctree
diacamma/asso/docs/build_fr/doctrees/index.doctree
diacamma/asso/docs/build_fr/doctrees/presentation.doctree
diacamma/asso/docs/en/Makefile
diacamma/asso/docs/en/conf.py
diacamma/asso/docs/en/first_step.rst
diacamma/asso/docs/en/index.rst
diacamma/asso/docs/en/presentation.rst
diacamma/asso/docs/fr/Makefile
diacamma/asso/docs/fr/conf.py
diacamma/asso/docs/fr/first_step.rst
diacamma/asso/docs/fr/index.rst
diacamma/asso/docs/fr/presentation.rst
diacamma/asso/locale/en/LC_MESSAGES/django.mo
diacamma/asso/locale/en/LC_MESSAGES/django.po
diacamma/asso/locale/fr/LC_MESSAGES/django.mo
diacamma/asso/locale/fr/LC_MESSAGES/django.po
diacamma/asso/migrations/0001_initial.py
diacamma/asso/migrations/0002_addon.py
diacamma/asso/migrations/__init__.py
diacamma/asso/migrations/__pycache__/0001_initial.cpython-39.pyc
diacamma/asso/migrations/__pycache__/0002_addon.cpython-39.pyc
diacamma/asso/migrations/__pycache__/__init__.cpython-39.pyc
diacamma/asso/pdf/build_fr/doctrees/environment.pickle
diacamma/asso/pdf/build_fr/doctrees/index.doctree
diacamma/asso/pdf/build_fr/doctrees/CORE/architecture.doctree
diacamma/asso/pdf/build_fr/doctrees/CORE/groups.doctree
diacamma_asso-2.7.5.25071011.dist-info/licenses/LICENSE
diacamma_asso-2.7.5.25071011.dist-info/METADATA
diacamma_asso-2.7.5.25071011.dist-info/WHEEL
diacamma_asso-2.7.5.25071011.dist-info/top_level.txt
diacamma_asso-2.7.5.25071011.dist-info/RECORD
